engine/__init__.py
engine/base_client.py
engine/config.py
engine/config_loader.py
engine/db_inspector.py
engine/message_broker.py
engine/mqtt_monitor.py
engine/orchestrator.py
engine/queue_monitor.py
engine/rabbitmq_monitor.py
engine/runner.py
engine/scenario.py
engine/clients/__init__.py
engine/clients/base.py
engine/clients/generic.py
testing_engine_core-0.5.0.dist-info/METADATA
testing_engine_core-0.5.0.dist-info/WHEEL
testing_engine_core-0.5.0.dist-info/top_level.txt
testing_engine_core-0.5.0.dist-info/RECORD
